pdfplumber/__init__.py
pdfplumber/_typing.py
pdfplumber/_version.py
pdfplumber/cli.py
pdfplumber/container.py
pdfplumber/convert.py
pdfplumber/ctm.py
pdfplumber/display.py
pdfplumber/page.py
pdfplumber/pdf.py
pdfplumber/py.typed
pdfplumber/repair.py
pdfplumber/structure.py
pdfplumber/table.py
pdfplumber/utils/__init__.py
pdfplumber/utils/clustering.py
pdfplumber/utils/generic.py
pdfplumber/utils/geometry.py
pdfplumber/utils/pdfinternals.py
pdfplumber/utils/text.py
pdfplumber-0.11.3.dist-info/LICENSE.txt
pdfplumber-0.11.3.dist-info/METADATA
pdfplumber-0.11.3.dist-info/WHEEL
pdfplumber-0.11.3.dist-info/entry_points.txt
pdfplumber-0.11.3.dist-info/pbr.json
pdfplumber-0.11.3.dist-info/top_level.txt
pdfplumber-0.11.3.dist-info/RECORD
